paulstretch/__init__.py
paulstretch/main.py
paulstretch-0.1.2.dist-info/METADATA
paulstretch-0.1.2.dist-info/WHEEL
paulstretch-0.1.2.dist-info/licenses/LICENSE
paulstretch-0.1.2.dist-info/RECORD
