Metadata-Version: 2.4
Name: paulstretch
Version: 0.1.2
Summary: A modern Python implementation of Paul Nasca's extreme time stretch algorithm with minimal dependencies.
Author-email: Moritz Schaller <kontakt@moritz-schaller.de>
License-File: LICENSE
Requires-Python: >=3.9
Requires-Dist: numpy>=2
